candlestick_chart/__init__.py
candlestick_chart/__main__.py
candlestick_chart/candle.py
candlestick_chart/candle_set.py
candlestick_chart/chart.py
candlestick_chart/chart_data.py
candlestick_chart/chart_renderer.py
candlestick_chart/colors.py
candlestick_chart/constants.py
candlestick_chart/info_bar.py
candlestick_chart/py.typed
candlestick_chart/utils.py
candlestick_chart/volume_pane.py
candlestick_chart/y_axis.py
candlestick_chart-3.1.0.dist-info/METADATA
candlestick_chart-3.1.0.dist-info/WHEEL
candlestick_chart-3.1.0.dist-info/entry_points.txt
candlestick_chart-3.1.0.dist-info/licenses/LICENSE
candlestick_chart-3.1.0.dist-info/RECORD
