Metadata-Version: 2.3
Name: candlestick-chart
Version: 3.1.0
Summary: Draw candlesticks charts right into your terminal, using Python!
Project-URL: Homepage, https://pypi.org/project/py-candlestick-chart
Project-URL: Changelog, https://github.com/BoboTiG/py-candlestick-chart/blob/main/CHANGELOG.md
Project-URL: Source, https://github.com/BoboTiG/py-candlestick-chart
Project-URL: Sponsor, https://github.com/sponsors/BoboTiG
Project-URL: Tracker, https://github.com/BoboTiG/py-candlestick-chart/issues
Project-URL: Released Versions, https://github.com/BoboTiG/py-candlestick-chart/releases
Author-email: Mickaël Schoentgen <contact@tiger-222.fr>
Maintainer-email: Mickaël Schoentgen <contact@tiger-222.fr>
License: MIT License
License-File: LICENSE
Keywords: candle,candlestick,chart,cli,console,crypto,options,stock,stock-market,terminal,trading
Classifier: Development Status :: 5 - Production/Stable
Classifier: Environment :: Console
Classifier: Intended Audience :: Developers
Classifier: Intended Audience :: Education
Classifier: Intended Audience :: End Users/Desktop
Classifier: Intended Audience :: Financial and Insurance Industry
Classifier: License :: OSI Approved :: MIT License
Classifier: Programming Language :: Python
Classifier: Programming Language :: Python :: 3
Classifier: Programming Language :: Python :: 3 :: Only
Classifier: Programming Language :: Python :: 3.10
Classifier: Programming Language :: Python :: 3.11
Classifier: Programming Language :: Python :: 3.12
Classifier: Programming Language :: Python :: 3.13
Classifier: Programming Language :: Python :: 3.14
Classifier: Programming Language :: Python :: Implementation :: CPython
Classifier: Topic :: Multimedia :: Graphics :: Viewers
Classifier: Topic :: Office/Business :: Financial
Classifier: Topic :: Scientific/Engineering :: Visualization
Classifier: Topic :: Software Development :: Libraries :: Python Modules
Classifier: Topic :: Software Development :: User Interfaces
Classifier: Topic :: Terminals
Requires-Python: >=3.10
Provides-Extra: dev
Requires-Dist: build==1.2.2.post1; extra == 'dev'
Requires-Dist: twine==5.1.1; extra == 'dev'
Provides-Extra: test
Requires-Dist: mypy==1.13.0; extra == 'test'
Requires-Dist: pytest-cov==6.0.0; extra == 'test'
Requires-Dist: pytest==8.3.3; extra == 'test'
Requires-Dist: requests==2.32.3; extra == 'test'
Requires-Dist: rich==13.9.4; extra == 'test'
Requires-Dist: ruff==0.7.2; extra == 'test'
Requires-Dist: types-requests; extra == 'test'
